setup.py
shinkenplugins/__init__.py
shinkenplugins.plugins.drupal_cache.egg-info/PKG-INFO
shinkenplugins.plugins.drupal_cache.egg-info/SOURCES.txt
shinkenplugins.plugins.drupal_cache.egg-info/dependency_links.txt
shinkenplugins.plugins.drupal_cache.egg-info/entry_points.txt
shinkenplugins.plugins.drupal_cache.egg-info/namespace_packages.txt
shinkenplugins.plugins.drupal_cache.egg-info/requires.txt
shinkenplugins.plugins.drupal_cache.egg-info/top_level.txt
shinkenplugins/plugins/__init__.py
shinkenplugins/plugins/drupal_cache/__init__.py
shinkenplugins/plugins/drupal_cache/drupal_cache.py